{"items": [{"_id": "5c6687d65e9d882c8841f0fd","_tpl": "55d7217a4bdc2d86028b456d"},{"_id": "5c6687d65e9d882c8841f121","_tpl": "557ffd194bdc2d28148b457f","parentId": "5c6687d65e9d882c8841f0fd","slotId": "Pockets"},{"_id": "5c6687d65e9d882c8841f0fc","_tpl": "566abbc34bdc2d92178b4576"},{"_id": "5c6687d65e9d882c8841f0ff","_tpl": "5963866b86f7747bfa1c4462"},{"_id": "5c6687d65e9d882c8841f0fe","_tpl": "5963866286f7747bf429b572"},{"_id": "I55145562612199996ypEkOo","_tpl": "572b7adb24597762ae139821","parentId": "5c6687d65e9d882c8841f0fd","slotId": "TacticalVest"},{"_id": "I081939371711993741pVK6S","_tpl": "5aafa857e5b5b00018480968","parentId": "5c6687d65e9d882c8841f0fd","slotId": "FirstPrimaryWeapon","upd": {"Repairable": {"MaxDurability": 100,"Durability": 100}}},{"_id": "I55145566517532559gdZnSk","_tpl": "5addccf45acfc400185c2989","parentId": "I081939371711993741pVK6S","slotId": "mod_magazine"},{"_id": "I551455626322046020FOPtO","_tpl": "5a608bf24f39f98ffc77720e","parentId": "I55145566517532559gdZnSk","slotId": "cartridges","upd": {"StackObjectsCount": 50}},{"_id": "I08193937783193590850UXS","_tpl": "5aaf8e43e5b5b00015693246","parentId": "I081939371711993741pVK6S","slotId": "mod_stock","upd": {"SpawnedInSession": true}},{"_id": "I081939371647193692wNaOt","_tpl": "5aaf9d53e5b5b00015042a52","parentId": "I081939371711993741pVK6S","slotId": "mod_barrel","upd": {"SpawnedInSession": true}},{"_id": "I081939376824798939f3X8Z","_tpl": "5abcbb20d8ce87001773e258","parentId": "I081939371711993741pVK6S","slotId": "mod_sight_rear","upd": {"SpawnedInSession": true}},{"_id": "I081939379294627815m6kt0","_tpl": "5addbfe15acfc4001a5fc58b","parentId": "I081939371711993741pVK6S","slotId": "mod_mount","upd": {"SpawnedInSession": true}},{"_id": "I081939373913482184QNYPZ","_tpl": "5addbfd15acfc40015621bde","parentId": "I08193937783193590850UXS","slotId": "mod_mount","upd": {"SpawnedInSession": true}},{"_id": "I0819393739908438166VADD","_tpl": "5a7b483fe899ef0016170d15","parentId": "I081939373913482184QNYPZ","slotId": "mod_tactical","upd": {"SpawnedInSession": true}},{"_id": "I0819393731860424576FLhN","_tpl": "5ab3afb2d8ce87001660304d","parentId": "I081939371647193692wNaOt","slotId": "mod_muzzle","upd": {"SpawnedInSession": true}},{"_id": "I081939379372950302LqScd","_tpl": "5c7954d52e221600106f4cc7","parentId": "I0819393731860424576FLhN","slotId": "mod_muzzle","upd": {"SpawnedInSession": true}},{"_id": "I081939373717118772oAB1A","_tpl": "5c7955c22e221644f31bfd5e","parentId": "I081939379372950302LqScd","slotId": "mod_muzzle","upd": {"SpawnedInSession": true}},{"_id": "I081939375067699424sNsm6","_tpl": "57ac965c24597706be5f975c","parentId": "I081939379294627815m6kt0","slotId": "mod_scope","upd": {"SpawnedInSession": true}},{"_id": "I551455648540687449wS1hQ","_tpl": "5857a8bc2459772bad15db29","parentId": "5c6687d65e9d882c8841f0fd","slotId": "SecuredContainer"},{"_id": "I55145569896628327ttOkqJ","_tpl": "5a6086ea4f39f99cd479502f","parentId": "I551455648540687449wS1hQ","slotId": "main","upd": {"StackObjectsCount": 60}},{"_id": "I55145566556751757GUQN94","_tpl": "5e023e6e34d52a55c3304f71","parentId": "I551455648540687449wS1hQ","slotId": "main","upd": {"StackObjectsCount": 60}},{"_id": "I55145563969934783iiuVQ2","_tpl": "58dd3ad986f77403051cba8f","parentId": "I551455648540687449wS1hQ","slotId": "main","upd": {"StackObjectsCount": 60}},{"_id": "I55145563445768945jqIxbw","_tpl": "5a608bf24f39f98ffc77720e","parentId": "I551455648540687449wS1hQ","slotId": "main","upd": {"StackObjectsCount": 60}},{"_id": "I55145563095851770shamqH","_tpl": "5e023e53d4353e3302577c4c","parentId": "I551455648540687449wS1hQ","slotId": "main","upd": {"StackObjectsCount": 60}},{"_id": "I55145569438156812J1vHvQ","_tpl": "5e023e88277cce2b522ff2b1","parentId": "I551455648540687449wS1hQ","slotId": "main","upd": {"StackObjectsCount": 60}},{"_id": "I551455626760231610D7qoH","_tpl": "5e023e53d4353e3302577c4c","parentId": "I551455648540687449wS1hQ","slotId": "main","upd": {"StackObjectsCount": 60}},{"_id": "I551455616505987131NVXaP","_tpl": "5e023e88277cce2b522ff2b1","parentId": "I551455648540687449wS1hQ","slotId": "main","upd": {"StackObjectsCount": 60}},{"_id": "I55145564598910966EaPR4Z","_tpl": "5a6086ea4f39f99cd479502f","parentId": "I551455648540687449wS1hQ","slotId": "main","upd": {"StackObjectsCount": 60}},{"_id": "I55145561027996524ei4ffA","_tpl": "544fb37f4bdc2dee738b4567","parentId": "I55145562612199996ypEkOo","slotId": "2"},{"_id": "I55145562852627631pdCQOm","_tpl": "5addccf45acfc400185c2989","parentId": "I55145562612199996ypEkOo","slotId": "3","location": {"x": 0,"y": 0,"r": "Horizontal"}},{"_id": "I55145561605707919yZ9LNR","_tpl": "5a6086ea4f39f99cd479502f","parentId": "I55145562852627631pdCQOm","slotId": "cartridges","upd": {"StackObjectsCount": 50}},{"_id": "I55145566428205744YCY8bd","_tpl": "5e023e6e34d52a55c3304f71","parentId": "I55145562612199996ypEkOo","slotId": "1","upd": {"StackObjectsCount": 22}},{"_id": "I55145565459328183IfrrGz","_tpl": "5bead2e00db834001c062938","parentId": "5c6687d65e9d882c8841f0fd","slotId": "Scabbard"},{"_id": "I551455673430827180Mu1LS","_tpl": "5aa7cfc0e5b5b00015693143","parentId": "5c6687d65e9d882c8841f0fd","slotId": "Headwear"},{"_id": "I55145565827917319cPnqxN","_tpl": "572b7fa524597762b747ce82","parentId": "5c6687d65e9d882c8841f0fd","slotId": "FaceCover"},{"_id": "I55145561295492664og8s3e","_tpl": "5ca2151486f774244a3b8d30","parentId": "5c6687d65e9d882c8841f0fd","slotId": "ArmorVest","upd": {"Repairable": {"MaxDurability": 60,"Durability": 51}}}],"equipment": "5c6687d65e9d882c8841f0fd","stash": "5c6687d65e9d882c8841f0fc","questRaidItems": "5c6687d65e9d882c8841f0fe","questStashItems": "5c6687d65e9d882c8841f0ff","fastPanel": {}}